capetools/__init__.py
capetools/_nbdev.py
capetools/imports.py
capetools/modelling/__init__.py
capetools/modelling/mybifacialvf.py
capetools/modelling/mypvfactors.py
capetools/utils/__init__.py
capetools/utils/core.py
capetools/utils/matlab_io.py
capetools/utils/missing.py
capetools/utils/pandas_hacks.py
capetools/utils/plot.py
capetools/utils/tmy.py
pvtools/__init__.py
pvtools/_nbdev.py
pvtools/imports.py
pvtools/modelling/__init__.py
pvtools/modelling/mybifacialvf.py
pvtools/modelling/mypvfactors.py
pvtools/utils/__init__.py
pvtools/utils/core.py
pvtools/utils/matlab_io.py
pvtools/utils/missing.py
pvtools/utils/pandas_hacks.py
pvtools/utils/plot.py
pvtools/utils/tmy.py
pvtools-1.1.3.dist-info/LICENSE
pvtools-1.1.3.dist-info/METADATA
pvtools-1.1.3.dist-info/WHEEL
pvtools-1.1.3.dist-info/entry_points.txt
pvtools-1.1.3.dist-info/top_level.txt
pvtools-1.1.3.dist-info/RECORD
